gameboycore.cpython-35m-x86_64-linux-gnu.so
gameboycore-0.6.1.dist-info/WHEEL
gameboycore-0.6.1.dist-info/top_level.txt
gameboycore-0.6.1.dist-info/METADATA
gameboycore-0.6.1.dist-info/RECORD
