Metadata-Version: 2.1
Name: gameboycore
Version: 0.6.1
Summary: Python bindings for Gameboy Core
Home-page: https://github.com/nnarain/gameboycore-python
Author: Natesh Narain
Author-email: nnaraindev@gmail.com
License: MIT
Keywords: gameboy emulator emulation
Platform: UNKNOWN
Requires-Dist: pybind11 (>=2.3)
